{
  "book_id": "PSA",
  "latin_name": "Liber Psalmorum",
  "hebrew_name": "תְּהִלִּים",
  "english_name": "Psalms",
  "chapter": 94,
  "verses": [
    {
      "verse": 1,
      "latin_vulgate": "Psalmus ipsi David, quarta sabbati.   Deus ultionum Dominus ;  Deus ultionum libere egit. ",
      "hebrew_masoretic": "אֵל־נְקָמ֥וֹת יְהֹוָ֑ה אֵ֖ל נְקָמ֣וֹת הוֹפִֽיעַ׃",
      "king_james": "O Lord God, to whom vengeance belongeth; O God, to whom vengeance belongeth, shew thyself.",
      "refs": {
        "latin_vulgate": {
          "src": "93:1"
        }
      }
    },
    {
      "verse": 2,
      "latin_vulgate": " Exaltare, qui judicas terram ;  redde retributionem superbis. ",
      "hebrew_masoretic": "הִ֭נָּשֵׂא שֹׁפֵ֣ט הָאָ֑רֶץ הָשֵׁ֥ב גְּ֝מ֗וּל עַל־גֵּאִֽים׃",
      "king_james": "Lift up thyself, thou judge of the earth: render a reward to the proud.",
      "refs": {
        "latin_vulgate": {
          "src": "93:2"
        }
      }
    },
    {
      "verse": 3,
      "latin_vulgate": " Usquequo peccatores, Domine,  usquequo peccatores gloriabuntur ; ",
      "hebrew_masoretic": "עַד־מָתַ֖י רְשָׁעִ֥ים ׀ יְהֹוָ֑ה עַד־מָ֝תַ֗י רְשָׁעִ֥ים יַעֲלֹֽזוּ׃",
      "king_james": "Lord, how long shall the wicked, how long shall the wicked triumph?",
      "refs": {
        "latin_vulgate": {
          "src": "93:3"
        }
      }
    },
    {
      "verse": 4,
      "latin_vulgate": " effabuntur et loquentur iniquitatem ;  loquentur omnes qui operantur injustitiam ? ",
      "hebrew_masoretic": "יַבִּ֣יעוּ יְדַבְּר֣וּ עָתָ֑ק יִ֝תְאַמְּר֗וּ כׇּל־פֹּ֥עֲלֵי אָֽוֶן׃",
      "king_james": "How long shall they utter and speak hard things? and all the workers of iniquity boast themselves?",
      "refs": {
        "latin_vulgate": {
          "src": "93:4"
        }
      }
    },
    {
      "verse": 5,
      "latin_vulgate": " Populum tuum, Domine, humiliaverunt,  et hæreditatem tuam vexaverunt. ",
      "hebrew_masoretic": "עַמְּךָ֣ יְהֹוָ֣ה יְדַכְּא֑וּ וְֽנַחֲלָתְךָ֥ יְעַנּֽוּ׃",
      "king_james": "They break in pieces thy people, O Lord, and afflict thine heritage.",
      "refs": {
        "latin_vulgate": {
          "src": "93:5"
        }
      }
    },
    {
      "verse": 6,
      "latin_vulgate": " Viduam et advenam interfecerunt,  et pupillos occiderunt. ",
      "hebrew_masoretic": "אַלְמָנָ֣ה וְגֵ֣ר יַהֲרֹ֑גוּ וִ֖יתוֹמִ֣ים יְרַצֵּֽחוּ׃",
      "king_james": "They slay the widow and the stranger, and murder the fatherless.",
      "refs": {
        "latin_vulgate": {
          "src": "93:6"
        }
      }
    },
    {
      "verse": 7,
      "latin_vulgate": " Et dixerunt : Non videbit Dominus,  nec intelliget Deus Jacob. ",
      "hebrew_masoretic": "וַ֭יֹּ֣אמְרוּ לֹ֣א יִרְאֶה־יָּ֑הּ וְלֹא־יָ֝בִ֗ין אֱלֹהֵ֥י יַעֲקֹֽב׃",
      "king_james": "Yet they say, The Lord shall not see, neither shall the God of Jacob regard it.",
      "refs": {
        "latin_vulgate": {
          "src": "93:7"
        }
      }
    },
    {
      "verse": 8,
      "latin_vulgate": " Intelligite, insipientes in populo ;  et stulti, aliquando sapite. ",
      "hebrew_masoretic": "בִּ֭ינוּ בֹּעֲרִ֣ים בָּעָ֑ם וּ֝כְסִילִ֗ים מָתַ֥י תַּשְׂכִּֽילוּ׃",
      "king_james": "Understand, ye brutish among the people: and ye fools, when will ye be wise?",
      "refs": {
        "latin_vulgate": {
          "src": "93:8"
        }
      }
    },
    {
      "verse": 9,
      "latin_vulgate": " Qui plantavit aurem non audiet ?  aut qui finxit oculum non considerat ? ",
      "hebrew_masoretic": "הֲנֹ֣טַֽע אֹ֭זֶן הֲלֹ֣א יִשְׁמָ֑ע אִֽם־יֹ֥צֵֽר עַ֝֗יִן הֲלֹ֣א יַבִּֽיט׃",
      "king_james": "He that planted the ear, shall he not hear? he that formed the eye, shall he not see?",
      "refs": {
        "latin_vulgate": {
          "src": "93:9"
        }
      }
    },
    {
      "verse": 10,
      "latin_vulgate": " Qui corripit gentes non arguet,  qui docet hominem scientiam ? ",
      "hebrew_masoretic": "הֲיֹסֵ֣ר גּ֭וֹיִם הֲלֹ֣א יוֹכִ֑יחַ הַֽמְלַמֵּ֖ד אָדָ֣ם דָּֽעַת׃",
      "king_james": "He that chastiseth the heathen, shall not he correct? he that teacheth man knowledge, shall not he know?",
      "refs": {
        "latin_vulgate": {
          "src": "93:10"
        }
      }
    },
    {
      "verse": 11,
      "latin_vulgate": " Dominus scit cogitationes hominum,  quoniam vanæ sunt. ",
      "hebrew_masoretic": "יְֽהֹוָ֗ה יֹ֭דֵעַ מַחְשְׁב֣וֹת אָדָ֑ם כִּי־הֵ֥מָּה הָֽבֶל׃",
      "king_james": "The Lord knoweth the thoughts of man, that they are vanity.",
      "refs": {
        "latin_vulgate": {
          "src": "93:11"
        }
      }
    },
    {
      "verse": 12,
      "latin_vulgate": " Beatus homo quem tu erudieris, Domine,  et de lege tua docueris eum : ",
      "hebrew_masoretic": "אַשְׁרֵ֤י ׀ הַגֶּ֣בֶר אֲשֶׁר־תְּיַסְּרֶ֣נּוּ יָּ֑הּ וּֽמִתּוֹרָתְךָ֥ תְלַמְּדֶֽנּוּ׃",
      "king_james": "Blessed is the man whom thou chastenest, O Lord, and teachest him out of thy law;",
      "refs": {
        "latin_vulgate": {
          "src": "93:12"
        }
      }
    },
    {
      "verse": 13,
      "latin_vulgate": " ut mitiges ei a diebus malis,  donec fodiatur peccatori fovea. ",
      "hebrew_masoretic": "לְהַשְׁקִ֣יט ל֭וֹ מִ֣ימֵי רָ֑ע עַ֤ד יִכָּרֶ֖ה לָרָשָׁ֣ע שָֽׁחַת׃",
      "king_james": "That thou mayest give him rest from the days of adversity, until the pit be digged for the wicked.",
      "refs": {
        "latin_vulgate": {
          "src": "93:13"
        }
      }
    },
    {
      "verse": 14,
      "latin_vulgate": " Quia non repellet Dominus plebem suam,  et hæreditatem suam non derelinquet, ",
      "hebrew_masoretic": "כִּ֤י ׀ לֹא־יִטֹּ֣שׁ יְהֹוָ֣ה עַמּ֑וֹ וְ֝נַחֲלָת֗וֹ לֹ֣א יַעֲזֹֽב׃",
      "king_james": "For the Lord will not cast off his people, neither will he forsake his inheritance.",
      "refs": {
        "latin_vulgate": {
          "src": "93:14"
        }
      }
    },
    {
      "verse": 15,
      "latin_vulgate": " quoadusque justitia convertatur in judicium :  et qui juxta illam, omnes qui recto sunt corde. ",
      "hebrew_masoretic": "כִּֽי־עַד־צֶ֭דֶק יָשׁ֣וּב מִשְׁפָּ֑ט וְ֝אַחֲרָ֗יו כׇּל־יִשְׁרֵי־לֵֽב׃",
      "king_james": "But judgment shall return unto righteousness: and all the upright in heart shall follow it.",
      "refs": {
        "latin_vulgate": {
          "src": "93:15"
        }
      }
    },
    {
      "verse": 16,
      "latin_vulgate": " Quis consurget mihi adversus malignantes ?  aut quis stabit mecum adversus operantes iniquitatem ? ",
      "hebrew_masoretic": "מִֽי־יָק֣וּם לִ֭י עִם־מְרֵעִ֑ים מִי־יִתְיַצֵּ֥ב לִ֝֗י עִם־פֹּ֥עֲלֵי אָֽוֶן׃",
      "king_james": "Who will rise up for me against the evildoers? or who will stand up for me against the workers of iniquity?",
      "refs": {
        "latin_vulgate": {
          "src": "93:16"
        }
      }
    },
    {
      "verse": 17,
      "latin_vulgate": " Nisi quia Dominus adjuvit me,  paulominus habitasset in inferno anima mea. ",
      "hebrew_masoretic": "לוּלֵ֣י יְ֭הֹוָה עֶזְרָ֣תָה לִּ֑י כִּמְעַ֓ט ׀ שָׁכְנָ֖ה דוּמָ֣ה נַפְשִֽׁי׃",
      "king_james": "Unless the Lord had been my help, my soul had almost dwelt in silence.",
      "refs": {
        "latin_vulgate": {
          "src": "93:17"
        }
      }
    },
    {
      "verse": 18,
      "latin_vulgate": " Si dicebam : Motus est pes meus :  misericordia tua, Domine, adjuvabat me. ",
      "hebrew_masoretic": "אִם־אָ֭מַרְתִּי מָ֣טָה רַגְלִ֑י חַסְדְּךָ֥ יְ֝הֹוָ֗ה יִסְעָדֵֽנִי׃",
      "king_james": "When I said, My foot slippeth; thy mercy, O Lord, held me up.",
      "refs": {
        "latin_vulgate": {
          "src": "93:18"
        }
      }
    },
    {
      "verse": 19,
      "latin_vulgate": " Secundum multitudinem dolorum meorum in corde meo,  consolationes tuæ lætificaverunt animam meam. ",
      "hebrew_masoretic": "בְּרֹ֣ב שַׂרְעַפַּ֣י בְּקִרְבִּ֑י תַּ֝נְחוּמֶ֗יךָ יְֽשַׁעַשְׁע֥וּ נַפְשִֽׁי׃",
      "king_james": "In the multitude of my thoughts within me thy comforts delight my soul.",
      "refs": {
        "latin_vulgate": {
          "src": "93:19"
        }
      }
    },
    {
      "verse": 20,
      "latin_vulgate": " Numquid adhæret tibi sedes iniquitatis,  qui fingis laborem in præcepto ? ",
      "hebrew_masoretic": "הַֽ֭יְחׇבְרְךָ כִּסֵּ֣א הַוּ֑וֹת יֹצֵ֖ר עָמָ֣ל עֲלֵי־חֹֽק׃",
      "king_james": "Shall the throne of iniquity have fellowship with thee, which frameth mischief by a law?",
      "refs": {
        "latin_vulgate": {
          "src": "93:20"
        }
      }
    },
    {
      "verse": 21,
      "latin_vulgate": " Captabunt in animam justi,  et sanguinem innocentem condemnabunt. ",
      "hebrew_masoretic": "יָ֭גוֹדּוּ עַל־נֶ֣פֶשׁ צַדִּ֑יק וְדָ֖ם נָקִ֣י יַרְשִֽׁיעוּ׃",
      "king_james": "They gather themselves together against the soul of the righteous, and condemn the innocent blood.",
      "refs": {
        "latin_vulgate": {
          "src": "93:21"
        }
      }
    },
    {
      "verse": 22,
      "latin_vulgate": " Et factus est mihi Dominus in refugium,  et Deus meus in adjutorium spei meæ. ",
      "hebrew_masoretic": "וַיְהִ֬י יְהֹוָ֣ה לִ֣י לְמִשְׂגָּ֑ב וֵ֝אלֹהַ֗י לְצ֣וּר מַחְסִֽי׃",
      "king_james": "But the Lord is my defence; and my God is the rock of my refuge.",
      "refs": {
        "latin_vulgate": {
          "src": "93:22"
        }
      }
    },
    {
      "verse": 23,
      "latin_vulgate": " Et reddet illis iniquitatem ipsorum,  et in malitia eorum disperdet eos :  disperdet illos Dominus Deus noster.  ",
      "hebrew_masoretic": "וַיָּ֤שֶׁב עֲלֵיהֶ֨ם ׀ אֶת־אוֹנָ֗ם וּבְרָעָתָ֥ם יַצְמִיתֵ֑ם יַ֝צְמִיתֵ֗ם יְהֹוָ֥ה אֱלֹהֵֽינוּ׃ {פ}",
      "king_james": "And he shall bring upon them their own iniquity, and shall cut them off in their own wickedness; yea, the Lord our God shall cut them off. ",
      "refs": {
        "latin_vulgate": {
          "src": "93:23"
        }
      }
    }
  ]
}
