{
  "strong": "G0283",
  "lemma": "ἀμίαντος",
  "translit": "amíantos",
  "lang": "grc",
  "pos": "G:A",
  "glosses": {
    "en": [
      {
        "text": "from G0001 (as a negative particle) and a derivative of G3392; unsoiled, i.e. (figuratively) pure",
        "src": "strongs-greek"
      },
      {
        "text": "pure",
        "src": "tbesg"
      }
    ]
  },
  "senses": [
    {
      "id": 1,
      "gloss_en": "from G0001 (as a negative particle) and a derivative of G3392; unsoiled, i.e. (figuratively) pure",
      "domain": null
    }
  ],
  "domains": [],
  "root": "G0001",
  "sources": [
    "strongs-greek",
    "tbesg"
  ]
}