{
  "strong": "G0320",
  "lemma": "ἀνάγνωσις",
  "translit": "anágnōsis",
  "lang": "grc",
  "pos": "G:N-F",
  "glosses": {
    "en": [
      {
        "text": "from G0314; (the act of) reading",
        "src": "strongs-greek"
      },
      {
        "text": "reading",
        "src": "tbesg"
      }
    ]
  },
  "senses": [
    {
      "id": 1,
      "gloss_en": "from G0314; (the act of) reading",
      "domain": null
    }
  ],
  "domains": [],
  "root": "G0314",
  "sources": [
    "strongs-greek",
    "tbesg"
  ]
}