{
  "strong": "G0352",
  "lemma": "ἀνακύπτω",
  "translit": "anakýptō",
  "lang": "grc",
  "pos": "G:V",
  "glosses": {
    "en": [
      {
        "text": "from G0303 (in the sense of reversal) and G2955; to unbend, i.e. rise; figuratively, be elated",
        "src": "strongs-greek"
      },
      {
        "text": "to straighten up",
        "src": "tbesg"
      }
    ]
  },
  "senses": [
    {
      "id": 1,
      "gloss_en": "from G0303 (in the sense of reversal) and G2955; to unbend, i.e. rise; figuratively, be elated",
      "domain": null
    }
  ],
  "domains": [],
  "root": "G0303",
  "sources": [
    "strongs-greek",
    "tbesg"
  ]
}