{
  "strong": "G0367",
  "lemma": "Ἀνανίας",
  "translit": "Ananías",
  "lang": "grc",
  "pos": "N:N-M-P",
  "glosses": {
    "en": [
      {
        "text": "of Hebrew origin (H2608); Ananias, the name of three Israelites",
        "src": "strongs-greek"
      },
      {
        "text": "Ananias",
        "src": "tbesg"
      }
    ]
  },
  "senses": [
    {
      "id": 1,
      "gloss_en": "of Hebrew origin (H2608); Ananias, the name of three Israelites",
      "domain": null
    }
  ],
  "domains": [],
  "root": null,
  "sources": [
    "strongs-greek",
    "tbesg"
  ]
}