{
  "strong": "G0854",
  "lemma": "ἀφανισμός",
  "translit": "aphanismós",
  "lang": "grc",
  "pos": "G:N-M",
  "glosses": {
    "en": [
      {
        "text": "from G0853; disappearance, i.e. (figuratively) abrogation",
        "src": "strongs-greek"
      },
      {
        "text": "disappearance",
        "src": "tbesg"
      }
    ]
  },
  "senses": [
    {
      "id": 1,
      "gloss_en": "from G0853; disappearance, i.e. (figuratively) abrogation",
      "domain": null
    }
  ],
  "domains": [],
  "root": "G0853",
  "sources": [
    "strongs-greek",
    "tbesg"
  ]
}