{
  "strong": "G0918",
  "lemma": "Βαρθολομαῖος",
  "translit": "Bartholomaîos",
  "lang": "grc",
  "pos": "",
  "glosses": {
    "en": [
      {
        "text": "son of Tolmai; Bar-tholomæus, a Christian apostle",
        "src": "strongs-greek"
      },
      {
        "text": "Bartholomew",
        "src": "tbesg"
      }
    ]
  },
  "senses": [
    {
      "id": 1,
      "gloss_en": "son of Tolmai; Bar-tholomæus, a Christian apostle",
      "domain": null
    }
  ],
  "domains": [],
  "root": null,
  "sources": [
    "strongs-greek",
    "tbesg"
  ]
}