{
  "strong": "G0914",
  "lemma": "Βαραχίας",
  "translit": "Barachías",
  "lang": "grc",
  "pos": "",
  "glosses": {
    "en": [
      {
        "text": "Barachias (i.e. Berechijah), an Israelite",
        "src": "strongs-greek"
      },
      {
        "text": "Barachiah",
        "src": "tbesg"
      }
    ]
  },
  "senses": [
    {
      "id": 1,
      "gloss_en": "Barachias (i.e. Berechijah), an Israelite",
      "domain": null
    }
  ],
  "domains": [],
  "root": null,
  "sources": [
    "strongs-greek",
    "tbesg"
  ]
}