{
  "strong": "G1129",
  "lemma": "γυμνασία",
  "translit": "gymnasía",
  "lang": "grc",
  "pos": "",
  "glosses": {
    "en": [
      {
        "text": "training, i.e. (figuratively) asceticism",
        "src": "strongs-greek"
      },
      {
        "text": "training",
        "src": "tbesg"
      }
    ]
  },
  "senses": [
    {
      "id": 1,
      "gloss_en": "training, i.e. (figuratively) asceticism",
      "domain": null
    }
  ],
  "domains": [],
  "root": "G1128",
  "sources": [
    "strongs-greek",
    "tbesg"
  ]
}