{
  "strong": "G1218",
  "lemma": "δῆμος",
  "translit": "dēmos",
  "lang": "grc",
  "pos": "G:N-M",
  "glosses": {
    "en": [
      {
        "text": "from G1210; the public (as bound together socially)",
        "src": "strongs-greek"
      },
      {
        "text": "people",
        "src": "tbesg"
      }
    ]
  },
  "senses": [
    {
      "id": 1,
      "gloss_en": "from G1210; the public (as bound together socially)",
      "domain": null
    }
  ],
  "domains": [
    "11.78"
  ],
  "root": "G1210",
  "sources": [
    "strongs-greek",
    "tbesg",
    "ln-map"
  ]
}