{
  "strong": "G1343",
  "lemma": "δικαιοσύνη",
  "translit": "dikaiosýnē",
  "lang": "grc",
  "pos": "",
  "glosses": {
    "en": [
      {
        "text": "equity (of character or act); specially (Christian) justification",
        "src": "strongs-greek"
      },
      {
        "text": "righteousness",
        "src": "tbesg"
      }
    ]
  },
  "senses": [
    {
      "id": 1,
      "gloss_en": "equity (of character or act); specially (Christian) justification",
      "domain": null
    }
  ],
  "domains": [],
  "root": "G1342",
  "sources": [
    "strongs-greek",
    "tbesg"
  ]
}