{
  "strong": "G1349",
  "lemma": "δίκη",
  "translit": "díkē",
  "lang": "grc",
  "pos": "",
  "glosses": {
    "en": [
      {
        "text": "right (as self-evident), i.e. justice (the principle, a decision, or its execution)",
        "src": "strongs-greek"
      },
      {
        "text": "condemnation",
        "src": "tbesg"
      }
    ]
  },
  "senses": [
    {
      "id": 1,
      "gloss_en": "right (as self-evident), i.e. justice (the principle, a decision, or its execution)",
      "domain": null
    }
  ],
  "domains": [],
  "root": "G1166",
  "sources": [
    "strongs-greek",
    "tbesg"
  ]
}