{
  "strong": "G1494",
  "lemma": "εἰδωλόθυτον",
  "translit": "eidōlóthyton",
  "lang": "grc",
  "pos": "",
  "glosses": {
    "en": [
      {
        "text": "an image-sacrifice, i.e. part of an idolatrous offering",
        "src": "strongs-greek"
      },
      {
        "text": "sacrificed to idols",
        "src": "tbesg"
      }
    ]
  },
  "senses": [
    {
      "id": 1,
      "gloss_en": "an image-sacrifice, i.e. part of an idolatrous offering",
      "domain": null
    }
  ],
  "domains": [],
  "root": "G1497",
  "sources": [
    "strongs-greek",
    "tbesg"
  ]
}