{
  "strong": "G2010",
  "lemma": "ἐπιτρέπω",
  "translit": "epitrépō",
  "lang": "grc",
  "pos": "G:V",
  "glosses": {
    "en": [
      {
        "text": "from G1909 and the base of G5157; to turn over (transfer), i.e. allow",
        "src": "strongs-greek"
      },
      {
        "text": "to permit",
        "src": "tbesg"
      }
    ]
  },
  "senses": [
    {
      "id": 1,
      "gloss_en": "from G1909 and the base of G5157; to turn over (transfer), i.e. allow",
      "domain": null
    }
  ],
  "domains": [],
  "root": "G1909",
  "sources": [
    "strongs-greek",
    "tbesg"
  ]
}