{
  "strong": "G2650",
  "lemma": "καταμένω",
  "translit": "kataménō",
  "lang": "grc",
  "pos": "",
  "glosses": {
    "en": [
      {
        "text": "to stay fully, i.e. reside",
        "src": "strongs-greek"
      },
      {
        "text": "to stay",
        "src": "tbesg"
      }
    ]
  },
  "senses": [
    {
      "id": 1,
      "gloss_en": "to stay fully, i.e. reside",
      "domain": null
    }
  ],
  "domains": [],
  "root": "G2596",
  "sources": [
    "strongs-greek",
    "tbesg"
  ]
}