{
  "strong": "G3083",
  "lemma": "λύτρον",
  "translit": "lýtron",
  "lang": "grc",
  "pos": "",
  "glosses": {
    "en": [
      {
        "text": "something to loosen with, i.e. a redemption price (figuratively, atonement)",
        "src": "strongs-greek"
      },
      {
        "text": "ransom",
        "src": "tbesg"
      }
    ]
  },
  "senses": [
    {
      "id": 1,
      "gloss_en": "something to loosen with, i.e. a redemption price (figuratively, atonement)",
      "domain": null
    }
  ],
  "domains": [],
  "root": "G3089",
  "sources": [
    "strongs-greek",
    "tbesg"
  ]
}