{
  "strong": "G3182",
  "lemma": "μεθύσκω",
  "translit": "methýskō",
  "lang": "grc",
  "pos": "G:V",
  "glosses": {
    "en": [
      {
        "text": "a prolonged (transitive) form of G3184; to intoxicate",
        "src": "strongs-greek"
      },
      {
        "text": "to get drunk",
        "src": "tbesg"
      }
    ]
  },
  "senses": [
    {
      "id": 1,
      "gloss_en": "a prolonged (transitive) form of G3184; to intoxicate",
      "domain": null
    }
  ],
  "domains": [
    "88.285"
  ],
  "root": "G3184",
  "sources": [
    "strongs-greek",
    "tbesg",
    "ln-map"
  ]
}