{
  "strong": "G3544",
  "lemma": "νομικός",
  "translit": "nomikós",
  "lang": "grc",
  "pos": "G:A",
  "glosses": {
    "en": [
      {
        "text": "from G3551; according (or pertaining) to law, i.e. legal (ceremonially); as noun, an expert in the (Mosaic) law",
        "src": "strongs-greek"
      },
      {
        "text": "lawyer",
        "src": "tbesg"
      }
    ]
  },
  "senses": [
    {
      "id": 1,
      "gloss_en": "from G3551; according (or pertaining) to law, i.e. legal (ceremonially); as noun, an expert in the (Mosaic) law",
      "domain": null
    }
  ],
  "domains": [],
  "root": "G3551",
  "sources": [
    "strongs-greek",
    "tbesg"
  ]
}