{
  "strong": "G3562",
  "lemma": "νουνεχῶς",
  "translit": "nounechōs",
  "lang": "grc",
  "pos": "G:ADV",
  "glosses": {
    "en": [
      {
        "text": "adverb from a comparative of the accusative case of G3563 and G2192; in a mind-having way, i.e. prudently",
        "src": "strongs-greek"
      },
      {
        "text": "wisely",
        "src": "tbesg"
      }
    ]
  },
  "senses": [
    {
      "id": 1,
      "gloss_en": "adverb from a comparative of the accusative case of G3563 and G2192; in a mind-having way, i.e. prudently",
      "domain": null
    }
  ],
  "domains": [
    "32.29"
  ],
  "root": "G3563",
  "sources": [
    "strongs-greek",
    "tbesg",
    "ln-map"
  ]
}