{
  "strong": "G3861",
  "lemma": "παράδοξος",
  "translit": "parádoxos",
  "lang": "grc",
  "pos": "",
  "glosses": {
    "en": [
      {
        "text": "contrary to expectation, i.e. extraordinary (\"paradox\")",
        "src": "strongs-greek"
      },
      {
        "text": "remarkable",
        "src": "tbesg"
      }
    ]
  },
  "senses": [
    {
      "id": 1,
      "gloss_en": "contrary to expectation, i.e. extraordinary (\"paradox\")",
      "domain": null
    }
  ],
  "domains": [],
  "root": "G3844",
  "sources": [
    "strongs-greek",
    "tbesg"
  ]
}