{
  "strong": "G3908",
  "lemma": "παρατίθημι",
  "translit": "paratíthēmi",
  "lang": "grc",
  "pos": "G:V",
  "glosses": {
    "en": [
      {
        "text": "from G3844 and G5087; to place alongside, i.e. present (food, truth); by implication, to deposit (as a trust or for protection)",
        "src": "strongs-greek"
      },
      {
        "text": "to set before",
        "src": "tbesg"
      }
    ]
  },
  "senses": [
    {
      "id": 1,
      "gloss_en": "from G3844 and G5087; to place alongside, i.e. present (food, truth); by implication, to deposit (as a trust or for protection)",
      "domain": null
    }
  ],
  "domains": [],
  "root": "G3844",
  "sources": [
    "strongs-greek",
    "tbesg"
  ]
}