{
  "strong": "G3963",
  "lemma": "Πάτμος",
  "translit": "Pátmos",
  "lang": "grc",
  "pos": "",
  "glosses": {
    "en": [
      {
        "text": "Patmus, an islet in the Mediterranean",
        "src": "strongs-greek"
      },
      {
        "text": "Patmos",
        "src": "tbesg"
      }
    ]
  },
  "senses": [
    {
      "id": 1,
      "gloss_en": "Patmus, an islet in the Mediterranean",
      "domain": null
    }
  ],
  "domains": [],
  "root": null,
  "sources": [
    "strongs-greek",
    "tbesg"
  ]
}