{
  "strong": "G4095",
  "lemma": "πίνω",
  "translit": "pínō",
  "lang": "grc",
  "pos": "",
  "glosses": {
    "en": [
      {
        "text": "to imbibe (literally or figuratively)",
        "src": "strongs-greek"
      },
      {
        "text": "to drink",
        "src": "tbesg"
      }
    ]
  },
  "senses": [
    {
      "id": 1,
      "gloss_en": "to imbibe (literally or figuratively)",
      "domain": null
    }
  ],
  "domains": [],
  "root": null,
  "sources": [
    "strongs-greek",
    "tbesg"
  ]
}