{
  "strong": "G4155",
  "lemma": "πνίγω",
  "translit": "pnígō",
  "lang": "grc",
  "pos": "",
  "glosses": {
    "en": [
      {
        "text": "to wheeze, i.e. (causative, by implication) to throttle or strangle (drown)",
        "src": "strongs-greek"
      },
      {
        "text": "to choke",
        "src": "tbesg"
      }
    ]
  },
  "senses": [
    {
      "id": 1,
      "gloss_en": "to wheeze, i.e. (causative, by implication) to throttle or strangle (drown)",
      "domain": null
    }
  ],
  "domains": [],
  "root": "G4154",
  "sources": [
    "strongs-greek",
    "tbesg"
  ]
}