{
  "strong": "G4152",
  "lemma": "πνευματικός",
  "translit": "pneumatikós",
  "lang": "grc",
  "pos": "",
  "glosses": {
    "en": [
      {
        "text": "non-carnal, i.e. (humanly) ethereal (as opposed to gross), or (dæmoniacally) a spirit (concretely), or (divinely) supernatural, regenerate, religious",
        "src": "strongs-greek"
      },
      {
        "text": "spiritual",
        "src": "tbesg"
      }
    ]
  },
  "senses": [
    {
      "id": 1,
      "gloss_en": "non-carnal, i.e. (humanly) ethereal (as opposed to gross), or (dæmoniacally) a spirit (concretely), or (divinely) supernatural, regenerate, religious",
      "domain": null
    }
  ],
  "domains": [],
  "root": "G4151",
  "sources": [
    "strongs-greek",
    "tbesg"
  ]
}