{
  "strong": "G4254",
  "lemma": "προάγω",
  "translit": "proágō",
  "lang": "grc",
  "pos": "G:V",
  "glosses": {
    "en": [
      {
        "text": "from G4253 and G0071; to lead forward (magisterially); intransitively, to precede (in place or time (participle, previous))",
        "src": "strongs-greek"
      },
      {
        "text": "to go/bring before",
        "src": "tbesg"
      }
    ]
  },
  "senses": [
    {
      "id": 1,
      "gloss_en": "from G4253 and G0071; to lead forward (magisterially); intransitively, to precede (in place or time (participle, previous))",
      "domain": null
    }
  ],
  "domains": [
    "13.114",
    "15.142",
    "15.143",
    "15.171",
    "36.25"
  ],
  "root": "G4253",
  "sources": [
    "strongs-greek",
    "tbesg",
    "ln-map"
  ]
}