{
  "strong": "G4307",
  "lemma": "πρόνοια",
  "translit": "prónoia",
  "lang": "grc",
  "pos": "G:N-F",
  "glosses": {
    "en": [
      {
        "text": "from G4306; forethought, i.e. provident care or supply",
        "src": "strongs-greek"
      },
      {
        "text": "foresight",
        "src": "tbesg"
      }
    ]
  },
  "senses": [
    {
      "id": 1,
      "gloss_en": "from G4306; forethought, i.e. provident care or supply",
      "domain": null
    }
  ],
  "domains": [
    "30.47"
  ],
  "root": "G4306",
  "sources": [
    "strongs-greek",
    "tbesg",
    "ln-map"
  ]
}