{
  "strong": "G4876",
  "lemma": "συναντάω",
  "translit": "synantáō",
  "lang": "grc",
  "pos": "",
  "glosses": {
    "en": [
      {
        "text": "to meet with; figuratively, to occur",
        "src": "strongs-greek"
      },
      {
        "text": "to meet",
        "src": "tbesg"
      }
    ]
  },
  "senses": [
    {
      "id": 1,
      "gloss_en": "to meet with; figuratively, to occur",
      "domain": null
    }
  ],
  "domains": [],
  "root": "G4862",
  "sources": [
    "strongs-greek",
    "tbesg"
  ]
}