{
  "strong": "G4919",
  "lemma": "συνθρύπτω",
  "translit": "synthrýptō",
  "lang": "grc",
  "pos": "",
  "glosses": {
    "en": [
      {
        "text": "to crush together, i.e. (figuratively) to dispirit",
        "src": "strongs-greek"
      },
      {
        "text": "to break",
        "src": "tbesg"
      }
    ]
  },
  "senses": [
    {
      "id": 1,
      "gloss_en": "to crush together, i.e. (figuratively) to dispirit",
      "domain": null
    }
  ],
  "domains": [],
  "root": "G4862",
  "sources": [
    "strongs-greek",
    "tbesg"
  ]
}