{
  "strong": "G4954",
  "lemma": "σύσσωμος",
  "translit": "sýssōmos",
  "lang": "grc",
  "pos": "G:A",
  "glosses": {
    "en": [
      {
        "text": "from G4862 and G4983; of a joint body, i.e. (figuratively) a fellow-member of the Christian community",
        "src": "strongs-greek"
      },
      {
        "text": "of the same body",
        "src": "tbesg"
      }
    ]
  },
  "senses": [
    {
      "id": 1,
      "gloss_en": "from G4862 and G4983; of a joint body, i.e. (figuratively) a fellow-member of the Christian community",
      "domain": null
    }
  ],
  "domains": [],
  "root": "G4862",
  "sources": [
    "strongs-greek",
    "tbesg"
  ]
}