{
  "strong": "G5214",
  "lemma": "ὑμνέω",
  "translit": "hymnéō",
  "lang": "grc",
  "pos": "G:V",
  "glosses": {
    "en": [
      {
        "text": "from G5215; to hymn, i.e. sing a religious ode; by implication, to celebrate (God) in song",
        "src": "strongs-greek"
      },
      {
        "text": "to praise",
        "src": "tbesg"
      }
    ]
  },
  "senses": [
    {
      "id": 1,
      "gloss_en": "from G5215; to hymn, i.e. sing a religious ode; by implication, to celebrate (God) in song",
      "domain": null
    }
  ],
  "domains": [],
  "root": "G5215",
  "sources": [
    "strongs-greek",
    "tbesg"
  ]
}