{
  "strong": "G5395",
  "lemma": "φλόξ",
  "translit": "phlóx",
  "lang": "grc",
  "pos": "G:N-F",
  "glosses": {
    "en": [
      {
        "text": "from a primary φλέγω (to \"flash\" or \"flame\"); a blaze",
        "src": "strongs-greek"
      },
      {
        "text": "flame",
        "src": "tbesg"
      }
    ]
  },
  "senses": [
    {
      "id": 1,
      "gloss_en": "from a primary φλέγω (to \"flash\" or \"flame\"); a blaze",
      "domain": null
    }
  ],
  "domains": [
    "2.4"
  ],
  "root": null,
  "sources": [
    "strongs-greek",
    "tbesg",
    "ln-map"
  ]
}