{
  "strong": "G5620",
  "lemma": "ὥστε",
  "translit": "hṓste",
  "lang": "grc",
  "pos": "G:CONJ",
  "glosses": {
    "en": [
      {
        "text": "from G5613 and G5037; so too, i.e. thus therefore (in various relations of consecution, as follow)",
        "src": "strongs-greek"
      },
      {
        "text": "so",
        "src": "tbesg"
      }
    ]
  },
  "senses": [
    {
      "id": 1,
      "gloss_en": "from G5613 and G5037; so too, i.e. thus therefore (in various relations of consecution, as follow)",
      "domain": null
    }
  ],
  "domains": [],
  "root": "G5613",
  "sources": [
    "strongs-greek",
    "tbesg"
  ]
}