{
  "book_id": "ISA",
  "latin_name": "Isaias",
  "hebrew_name": "יְשַׁעְיָהוּ",
  "english_name": "Isaiah",
  "chapter": 64,
  "verses": [
    {
      "verse": 1,
      "latin_vulgate": "Utinam dirumperes cælos, et descenderes ;  a facie tua montes defluerent ; ",
      "hebrew_masoretic": "כִּקְדֹ֧חַ אֵ֣שׁ הֲמָסִ֗ים מַ֚יִם תִּבְעֶה־אֵ֔שׁ לְהוֹדִ֥יעַ שִׁמְךָ֖ לְצָרֶ֑יךָ מִפָּנֶ֖יךָ גּוֹיִ֥ם יִרְגָּֽזוּ׃",
      "king_james": "Oh that thou wouldest rend the heavens, that thou wouldest come down, that the mountains might flow down at thy presence,"
    },
    {
      "verse": 2,
      "latin_vulgate": " sicut exustio ignis tabescerent,  aquæ arderent igni :  ut notum fieret nomen tuum inimicis tuis ;  a facie tua gentes turbarentur. ",
      "hebrew_masoretic": "כִּקְדֹ֧חַ אֵ֣שׁ הֲמָסִ֗ים מַ֚יִם תִּבְעֶה־אֵ֔שׁ לְהוֹדִ֥יעַ שִׁמְךָ֖ לְצָרֶ֑יךָ מִפָּנֶ֖יךָ גּוֹיִ֥ם יִרְגָּֽזוּ׃",
      "king_james": "As when the melting fire burneth, the fire causeth the waters to boil, to make thy name known to thine adversaries, that the nations may tremble at thy presence!",
      "refs": {
        "hebrew_masoretic": "64:1"
      }
    },
    {
      "verse": 3,
      "latin_vulgate": " Cum feceris mirabilia, non sustinebimus ;  descendisti, et a facie tua montes defluxerunt. ",
      "hebrew_masoretic": "בַּעֲשׂוֹתְךָ֥ נוֹרָא֖וֹת לֹ֣א נְקַוֶּ֑ה יָרַ֕דְתָּ מִפָּנֶ֖יךָ הָרִ֥ים נָזֹֽלּוּ׃ {ס}",
      "king_james": "When thou didst terrible things which we looked not for, thou camest down, the mountains flowed down at thy presence.",
      "refs": {
        "hebrew_masoretic": "64:2"
      }
    },
    {
      "verse": 4,
      "latin_vulgate": " A sæculo non audierunt, neque auribus perceperunt ;  oculus non vidit, Deus, absque te,  quæ præparasti exspectantibus te. ",
      "hebrew_masoretic": "וּמֵעוֹלָ֥ם לֹא־שָׁמְע֖וּ לֹ֣א הֶאֱזִ֑ינוּ עַ֣יִן לֹֽא־רָאָ֗תָה אֱלֹהִים֙ זוּלָ֣תְךָ֔ יַעֲשֶׂ֖ה לִמְחַכֵּה־לֽוֹ׃",
      "king_james": "For since the beginning of the world men have not heard, nor perceived by the ear, neither hath the eye seen, O God, beside thee, what he hath prepared for him that waiteth for him.",
      "refs": {
        "hebrew_masoretic": "64:3"
      }
    },
    {
      "verse": 5,
      "latin_vulgate": " Occurristi lætanti, et facienti justitiam ;  in viis tuis recordabuntur tui.  Ecce tu iratus es, et peccavimus ;  in ipsis fuimus semper, et salvabimur. ",
      "hebrew_masoretic": "פָּגַ֤עְתָּ אֶת־שָׂשׂ֙ וְעֹ֣שֵׂה צֶ֔דֶק בִּדְרָכֶ֖יךָ יִזְכְּר֑וּךָ הֵן־אַתָּ֤ה קָצַ֙פְתָּ֙ וַֽנֶּחֱטָ֔א בָּהֶ֥ם עוֹלָ֖ם וְנִוָּשֵֽׁעַ׃",
      "king_james": "Thou meetest him that rejoiceth and worketh righteousness, those that remember thee in thy ways: behold, thou art wroth; for we have sinned: in those is continuance, and we shall be saved.",
      "refs": {
        "hebrew_masoretic": "64:4"
      }
    },
    {
      "verse": 6,
      "latin_vulgate": " Et facti sumus ut immundus omnes nos,  et quasi pannus menstruatæ universæ justitiæ nostræ ;  et cecidimus quasi folium universi,  et iniquitates nostræ quasi ventus abstulerunt nos. ",
      "hebrew_masoretic": "וַנְּהִ֤י כַטָּמֵא֙ כֻּלָּ֔נוּ וּכְבֶ֥גֶד עִדִּ֖ים כׇּל־צִדְקֹתֵ֑ינוּ וַנָּ֤בֶל כֶּֽעָלֶה֙ כֻּלָּ֔נוּ וַעֲוֺנֵ֖נוּ כָּר֥וּחַ יִשָּׂאֻֽנוּ׃",
      "king_james": "But we are all as an unclean thing, and all our righteousnesses are as filthy rags; and we all do fade as a leaf; and our iniquities, like the wind, have taken us away.",
      "refs": {
        "hebrew_masoretic": "64:5"
      }
    },
    {
      "verse": 7,
      "latin_vulgate": " Non est qui invocet nomen tuum ;  qui consurgat, et teneat te.  Abscondisti faciem tuam a nobis,  et allisisti nos in manu iniquitatis nostræ. ",
      "hebrew_masoretic": "וְאֵין־קוֹרֵ֣א בְשִׁמְךָ֔ מִתְעוֹרֵ֖ר לְהַחֲזִ֣יק בָּ֑ךְ כִּֽי־הִסְתַּ֤רְתָּ פָנֶ֙יךָ֙ מִמֶּ֔נּוּ וַתְּמוּגֵ֖נוּ בְּיַד־עֲוֺנֵֽנוּ׃",
      "king_james": "And there is none that calleth upon thy name, that stirreth up himself to take hold of thee: for thou hast hid thy face from us, and hast consumed us, because of our iniquities.",
      "refs": {
        "hebrew_masoretic": "64:6"
      }
    },
    {
      "verse": 8,
      "latin_vulgate": " Et nunc, Domine, pater noster es tu,  nos vero lutum ;  et fictor noster tu,  et opera manuum tuarum omnes nos. ",
      "hebrew_masoretic": "וְעַתָּ֥ה יְהֹוָ֖ה אָבִ֣ינוּ אָ֑תָּה אֲנַ֤חְנוּ הַחֹ֙מֶר֙ וְאַתָּ֣ה יֹצְרֵ֔נוּ וּמַעֲשֵׂ֥ה יָדְךָ֖ כֻּלָּֽנוּ׃",
      "king_james": "But now, O Lord, thou art our father; we are the clay, and thou our potter; and we all are the work of thy hand.",
      "refs": {
        "hebrew_masoretic": "64:7"
      }
    },
    {
      "verse": 9,
      "latin_vulgate": " Ne irascaris, Domine, satis,  et ne ultra memineris iniquitatis nostræ ;  ecce, respice, populus tuus omnes nos. ",
      "hebrew_masoretic": "אַל־תִּקְצֹ֤ף יְהֹוָה֙ עַד־מְאֹ֔ד וְאַל־לָעַ֖ד תִּזְכֹּ֣ר עָוֺ֑ן הֵ֥ן הַבֶּט־נָ֖א עַמְּךָ֥ כֻלָּֽנוּ׃",
      "king_james": "Be not wroth very sore, O Lord, neither remember iniquity for ever: behold, see, we beseech thee, we are all thy people.",
      "refs": {
        "hebrew_masoretic": "64:8"
      }
    },
    {
      "verse": 10,
      "latin_vulgate": " Civitas Sancti tui facta est deserta,  Sion deserta facta est,  Jerusalem desolata est. ",
      "hebrew_masoretic": "עָרֵ֥י קׇדְשְׁךָ֖ הָי֣וּ מִדְבָּ֑ר צִיּוֹן֙ מִדְבָּ֣ר הָיָ֔תָה יְרוּשָׁלַ֖͏ִם שְׁמָמָֽה׃",
      "king_james": "Thy holy cities are a wilderness, Zion is a wilderness, Jerusalem a desolation.",
      "refs": {
        "hebrew_masoretic": "64:9"
      }
    },
    {
      "verse": 11,
      "latin_vulgate": " Domus sanctificationis nostræ et gloriæ nostræ,  ubi laudaverunt te patres nostri,  facta est in exustionem ignis,  et omnia desiderabilia nostra versa sunt in ruinas. ",
      "hebrew_masoretic": "בֵּ֧ית קׇדְשֵׁ֣נוּ וְתִפְאַרְתֵּ֗נוּ אֲשֶׁ֤ר הִֽלְל֙וּךָ֙ אֲבֹתֵ֔ינוּ הָיָ֖ה לִשְׂרֵ֣פַת אֵ֑שׁ וְכׇל־מַחֲמַדֵּ֖ינוּ הָיָ֥ה לְחׇרְבָּֽה׃",
      "king_james": "Our holy and our beautiful house, where our fathers praised thee, is burned up with fire: and all our pleasant things are laid waste.",
      "refs": {
        "hebrew_masoretic": "64:10"
      }
    },
    {
      "verse": 12,
      "latin_vulgate": " Numquid super his continebis te, Domine ;  tacebis, et affliges nos vehementer ?  ",
      "hebrew_masoretic": "הַעַל־אֵ֥לֶּה תִתְאַפַּ֖ק יְהֹוָ֑ה תֶּחֱשֶׁ֥ה וּתְעַנֵּ֖נוּ עַד־מְאֹֽד׃ {פ}",
      "king_james": "Wilt thou refrain thyself for these things, O Lord? wilt thou hold thy peace, and afflict us very sore? ",
      "refs": {
        "hebrew_masoretic": "64:11"
      }
    }
  ]
}
