{
  "book_id": "PSA",
  "chapter": 140,
  "source": "Swete 1909 (Public Domain)",
  "verses": [
    {
      "verse": 1,
      "greek_lxx": "Ψαλμὸς τῷ Δαυείδ. Κύριε, πρὸς σὲ ἐκέκραξα, εἰσάκουσόν μου· πρόσχες τῇ φωνῇ τῆς δεήσεώς μου ἐν τῷ κεκραγέναι με πρὸς σέ.",
      "refs": {
        "mt": {
          "src": "141:1"
        }
      }
    },
    {
      "verse": 2,
      "greek_lxx": "κατευθυνθήτω ἡ προσευχή μου ὡς θυμίαμα ἐνώπιόν σου, ἔπαρσις τῶν χειρῶν μου θυσία ἑσπερινή.",
      "refs": {
        "mt": {
          "src": "141:2"
        }
      }
    },
    {
      "verse": 3,
      "greek_lxx": "θοῦ, Κύριε, φυλακὴν τῷ στόματί μου, καὶ θύραν περιοχῆς περὶ τὰ χείλη μου.",
      "refs": {
        "mt": {
          "src": "141:3"
        }
      }
    },
    {
      "verse": 4,
      "greek_lxx": "μὴ ἐκκλίνῃς τὴν καρδίαν μου εἰς λόγους πονηρίας, τοῦ προφασίζεσθαι προφάσεις ἐν ἁμαρτίαις, σὺν ἀνθρώποις ἐργαζομένοις ἀνομίαν, καὶ οὐ μὴ συνδοιάσω μετὰ τῶν ἐκλεκτῶν αὐτῶν.",
      "refs": {
        "mt": {
          "src": "141:4"
        }
      }
    },
    {
      "verse": 5,
      "greek_lxx": "παιδεύσει με δίκαιος ἐν ἐλέει καὶ ἐλέγξει με, ἔλαιον δὲ ἁμαρτωλοῦ μὴ λιπανάτω τὴν κεφαλὴν μου· ὅτι ἔτι καὶ ἔτι ἡ προσευχή μου ἐν ταῖς εὐδοκίαις αὐτῶν.",
      "refs": {
        "mt": {
          "src": "141:5"
        }
      }
    },
    {
      "verse": 6,
      "greek_lxx": "κατεπόθησαν ἐχόμενα πέτρας οἱ κραταιοὶ αὐτῶν· ἀκούσονται τὰ ῥήματά μου, ὅτι ἠδυνήθησαν.",
      "refs": {
        "mt": {
          "src": "141:6"
        }
      }
    },
    {
      "verse": 7,
      "greek_lxx": "ὡσεὶ πάχος γῆς διερράγη ἐπὶ τῆς γῆς, διεσκορπίσθη τὰ ὀστᾶ ἡμῶν παρὰ τὸν ᾅδην.",
      "refs": {
        "mt": {
          "src": "141:7"
        }
      }
    },
    {
      "verse": 8,
      "greek_lxx": "ὅτι πρὸς σέ, Κύριε κύριε, οἱ ὀφθαλμοί μου, ἐπὶ σὲ ἤλπισα, μὴ ἀντανέλῃς τὴν ψυχήν μου·",
      "refs": {
        "mt": {
          "src": "141:8"
        }
      }
    },
    {
      "verse": 9,
      "greek_lxx": "φύλαξόν με ἀπὸ παγίδος ἧς συνεστήσαντό μοι, καὶ ἀπὸ σκανδάλων τῶν ἐργαζομένων τὴν ἀνομίαν.",
      "refs": {
        "mt": {
          "src": "141:9"
        }
      }
    },
    {
      "verse": 10,
      "greek_lxx": "πεσοῦνται ἐν ἀμφιβλήστρῳ αὐτοῦ ἁμαρτωλοί· κατὰ μόνας εἰμὶ ἐγὼ ἕως οὗ ἂν παρέλθω.",
      "refs": {
        "mt": {
          "src": "141:10"
        }
      }
    }
  ]
}
