{
  "strong": "H0978",
  "lemma": "בַּחֲרוּמִי",
  "translit": "Bachărûwmîy",
  "lang": "hbo",
  "pos": "a",
  "glosses": {
    "en": [
      {
        "text": "patrial from H0980 (by transposition); a Bacharumite or inhabitant of Bachurim",
        "src": "strongs-hebrew"
      }
    ]
  },
  "senses": [
    {
      "id": 1,
      "gloss_en": "patrial from H0980 (by transposition); a Bacharumite or inhabitant of Bachurim",
      "domain": null
    }
  ],
  "domains": [
    "003001006"
  ],
  "root": "H0980",
  "sources": [
    "strongs-hebrew",
    "sdbh"
  ]
}