{
  "strong": "H1194",
  "lemma": "בְּעֹן",
  "translit": "Bᵉʻôn",
  "lang": "hbo",
  "pos": "n-pr-loc",
  "glosses": {
    "en": [
      {
        "text": "probably a contraction of H1010; Beon, a place East of the Jordan",
        "src": "strongs-hebrew"
      }
    ]
  },
  "senses": [
    {
      "id": 1,
      "gloss_en": "probably a contraction of H1010; Beon, a place East of the Jordan",
      "domain": null
    }
  ],
  "domains": [],
  "root": "H1010",
  "sources": [
    "strongs-hebrew"
  ]
}