{
  "strong": "H2760",
  "lemma": "חָרַךְ",
  "translit": "chârak",
  "lang": "hbo",
  "pos": "v",
  "glosses": {
    "en": [
      {
        "text": "a primitive root; to braid (i.e. to entangle or snare) or catch (game) in anet",
        "src": "strongs-hebrew"
      }
    ]
  },
  "senses": [
    {
      "id": 1,
      "gloss_en": "a primitive root; to braid (i.e. to entangle or snare) or catch (game) in anet",
      "domain": null
    }
  ],
  "domains": [],
  "root": null,
  "sources": [
    "strongs-hebrew"
  ]
}