{
  "strong": "H2973",
  "lemma": "יָאַל",
  "translit": "yâʼal",
  "lang": "hbo",
  "pos": "v",
  "glosses": {
    "en": [
      {
        "text": "a primitive root; properly, to be slack, i.e. (figuratively) to be foolish",
        "src": "strongs-hebrew"
      }
    ]
  },
  "senses": [
    {
      "id": 1,
      "gloss_en": "a primitive root; properly, to be slack, i.e. (figuratively) to be foolish",
      "domain": null
    }
  ],
  "domains": [],
  "root": null,
  "sources": [
    "strongs-hebrew"
  ]
}