{
  "strong": "H3123",
  "lemma": "יוֹנָה",
  "translit": "yôwnâh",
  "lang": "hbo",
  "pos": "n-f",
  "glosses": {
    "en": [
      {
        "text": "probably from the same as H3196; a dove (apparently from the warmth of their mating)",
        "src": "strongs-hebrew"
      }
    ]
  },
  "senses": [
    {
      "id": 1,
      "gloss_en": "probably from the same as H3196; a dove (apparently from the warmth of their mating)",
      "domain": null
    }
  ],
  "domains": [],
  "root": "H3196",
  "sources": [
    "strongs-hebrew"
  ]
}