{
  "strong": "H3317",
  "lemma": "יִפְתַּח־אֵל",
  "translit": "Yiphtach-ʼêl",
  "lang": "hbo",
  "pos": "n-pr-loc",
  "glosses": {
    "en": [
      {
        "text": "from H6605 and H0410; God will open; Jiphtach-el, a place in Palestine",
        "src": "strongs-hebrew"
      }
    ]
  },
  "senses": [
    {
      "id": 1,
      "gloss_en": "from H6605 and H0410; God will open; Jiphtach-el, a place in Palestine",
      "domain": null
    }
  ],
  "domains": [],
  "root": "H6605",
  "sources": [
    "strongs-hebrew"
  ]
}