{
  "strong": "H3620",
  "lemma": "כְּלוּב",
  "translit": "Kᵉlûwb",
  "lang": "hbo",
  "pos": "n-pr-m",
  "glosses": {
    "en": [
      {
        "text": "the same as H3619xlit kᵉlûb corrected to kᵉlûwb; Kelub, the name of two Israelites",
        "src": "strongs-hebrew"
      }
    ]
  },
  "senses": [
    {
      "id": 1,
      "gloss_en": "the same as H3619xlit kᵉlûb corrected to kᵉlûwb; Kelub, the name of two Israelites",
      "domain": null
    }
  ],
  "domains": [
    "003001007"
  ],
  "root": "H3619",
  "sources": [
    "strongs-hebrew",
    "sdbh"
  ]
}