{
  "strong": "H3798",
  "lemma": "כִּתְלִישׁ",
  "translit": "Kithlîysh",
  "lang": "hbo",
  "pos": "n-pr-loc",
  "glosses": {
    "en": [
      {
        "text": "from H3796 and H0376; wall of a man; Kithlish, a place in Palestine",
        "src": "strongs-hebrew"
      }
    ]
  },
  "senses": [
    {
      "id": 1,
      "gloss_en": "from H3796 and H0376; wall of a man; Kithlish, a place in Palestine",
      "domain": null
    }
  ],
  "domains": [
    "003001010"
  ],
  "root": "H3796",
  "sources": [
    "strongs-hebrew",
    "sdbh"
  ]
}