{
  "strong": "H4424",
  "lemma": "מְלַטְיָה",
  "translit": "Mᵉlaṭyâh",
  "lang": "hbo",
  "pos": "n-pr-m",
  "glosses": {
    "en": [
      {
        "text": "from H4423 and H3050; (whom) Jah has delivered; Melatjah, a Gibeonite",
        "src": "strongs-hebrew"
      }
    ]
  },
  "senses": [
    {
      "id": 1,
      "gloss_en": "from H4423 and H3050; (whom) Jah has delivered; Melatjah, a Gibeonite",
      "domain": null
    }
  ],
  "domains": [],
  "root": "H4423",
  "sources": [
    "strongs-hebrew"
  ]
}