{
  "strong": "H4888",
  "lemma": "מִשְׁחָה",
  "translit": "mishchâh",
  "lang": "hbo",
  "pos": "n-f",
  "glosses": {
    "en": [
      {
        "text": "or ; from H4886; unction (the act); by implication, a consecratory gift",
        "src": "strongs-hebrew"
      }
    ]
  },
  "senses": [
    {
      "id": 1,
      "gloss_en": "or ; from H4886; unction (the act); by implication, a consecratory gift",
      "domain": null
    }
  ],
  "domains": [
    "001006007",
    "002002002008",
    "002002002008 002003002020"
  ],
  "root": null,
  "sources": [
    "strongs-hebrew",
    "sdbh"
  ]
}