{
  "strong": "H5073",
  "lemma": "נִדְבָּךְ",
  "translit": "nidbâk",
  "lang": "hbo",
  "pos": "n-m",
  "glosses": {
    "en": [
      {
        "text": "(Aramaic) from a root meaning to stick; a layer (of building materials)",
        "src": "strongs-hebrew"
      }
    ]
  },
  "senses": [
    {
      "id": 1,
      "gloss_en": "(Aramaic) from a root meaning to stick; a layer (of building materials)",
      "domain": null
    }
  ],
  "domains": [],
  "root": null,
  "sources": [
    "strongs-hebrew"
  ]
}