{
  "strong": "H6705",
  "lemma": "צָחַח",
  "translit": "tsâchach",
  "lang": "hbo",
  "pos": "v",
  "glosses": {
    "en": [
      {
        "text": "a primitive root; to glare, i.e. be dazzling white",
        "src": "strongs-hebrew"
      }
    ]
  },
  "senses": [
    {
      "id": 1,
      "gloss_en": "a primitive root; to glare, i.e. be dazzling white",
      "domain": null
    }
  ],
  "domains": [
    "002001001015 002001001049"
  ],
  "root": null,
  "sources": [
    "strongs-hebrew",
    "sdbh"
  ]
}