{
  "strong": "H7311",
  "lemma": "רוּם",
  "translit": "rûwm",
  "lang": "hbo",
  "pos": "v",
  "glosses": {
    "en": [
      {
        "text": "a primitive root; to be high actively, to rise or raise (in various applications, literally or figuratively)",
        "src": "strongs-hebrew"
      }
    ]
  },
  "senses": [
    {
      "id": 1,
      "gloss_en": "a primitive root; to be high actively, to rise or raise (in various applications, literally or figuratively)",
      "domain": null
    }
  ],
  "domains": [],
  "root": null,
  "sources": [
    "strongs-hebrew"
  ]
}