{
  "strong": "H7476",
  "lemma": "רַעְיוֹן",
  "translit": "raʻyôwn",
  "lang": "hbo",
  "pos": "n-m",
  "glosses": {
    "en": [
      {
        "text": "(Aramaic) corresponding to H7475; a grasp. i.e. (figuratively) mental conception",
        "src": "strongs-hebrew"
      }
    ]
  },
  "senses": [
    {
      "id": 1,
      "gloss_en": "(Aramaic) corresponding to H7475; a grasp. i.e. (figuratively) mental conception",
      "domain": null
    }
  ],
  "domains": [],
  "root": "H7475",
  "sources": [
    "strongs-hebrew"
  ]
}