{
  "strong": "H8530",
  "lemma": "תַּלְפִּיָּה",
  "translit": "talpîyâh",
  "lang": "hbo",
  "pos": "n-f",
  "glosses": {
    "en": [
      {
        "text": "feminine from an unused root meaning to tower; something tall, i.e. (plural collective) slenderness",
        "src": "strongs-hebrew"
      }
    ]
  },
  "senses": [
    {
      "id": 1,
      "gloss_en": "feminine from an unused root meaning to tower; something tall, i.e. (plural collective) slenderness",
      "domain": null
    }
  ],
  "domains": [],
  "root": null,
  "sources": [
    "strongs-hebrew"
  ]
}